{
  "Body": {
    "loc.x": [
      {
        "t": 0.0,
        "v": -0.0,
        "i": {
          "typ": "BAZIER",
          "cp1": {
            "t": 1.333,
            "v": -0.0
          },
          "cp2": {
            "t": 2.667,
            "v": -0.0
          }
        }
      },
      {
        "t": 10.0,
        "v": -0.0,
        "i": null
      }
    ],
    "loc.y": [
      {
        "t": 0.0,
        "v": 0.0,
        "i": {
          "typ": "BAZIER",
          "cp1": {
            "t": 1.333,
            "v": 0.0
          },
          "cp2": {
            "t": 2.667,
            "v": 0.0
          }
        }
      },
      {
        "t": 4.0,
        "v": -0.234,
        "i": {
          "typ": "BAZIER",
          "cp1": {
            "t": 4.667,
            "v": -0.352
          },
          "cp2": {
            "t": 5.333,
            "v": -0.563
          }
        }
      },
      {
        "t": 6.0,
        "v": -0.563,
        "i": {
          "typ": "BAZIER",
          "cp1": {
            "t": 7.333,
            "v": -0.563
          },
          "cp2": {
            "t": 8.667,
            "v": 0.0
          }
        }
      },
      {
        "t": 10.0,
        "v": 0.0,
        "i": null
      }
    ],
    "loc.z": [
      {
        "t": 0.0,
        "v": -0.0,
        "i": {
          "typ": "BAZIER",
          "cp1": {
            "t": 1.333,
            "v": -0.0
          },
          "cp2": {
            "t": 2.667,
            "v": -0.213
          }
        }
      },
      {
        "t": 4.0,
        "v": -0.213,
        "i": {
          "typ": "BAZIER",
          "cp1": {
            "t": 4.667,
            "v": -0.213
          },
          "cp2": {
            "t": 5.333,
            "v": -0.175
          }
        }
      },
      {
        "t": 6.0,
        "v": -0.138,
        "i": {
          "typ": "BAZIER",
          "cp1": {
            "t": 7.333,
            "v": -0.065
          },
          "cp2": {
            "t": 8.667,
            "v": -0.0
          }
        }
      },
      {
        "t": 10.0,
        "v": -0.0,
        "i": null
      }
    ],
    "rot_q.w": [
      {
        "t": 0.0,
        "v": 1.0,
        "i": {
          "typ": "BAZIER",
          "cp1": {
            "t": 1.159,
            "v": -0.077
          },
          "cp2": {
            "t": 2.667,
            "v": 0.198
          }
        }
      },
      {
        "t": 4.0,
        "v": -0.106,
        "i": {
          "typ": "BAZIER",
          "cp1": {
            "t": 4.667,
            "v": -0.257
          },
          "cp2": {
            "t": 5.295,
            "v": -0.555
          }
        }
      },
      {
        "t": 6.0,
        "v": -0.637,
        "i": {
          "typ": "BAZIER",
          "cp1": {
            "t": 7.338,
            "v": -0.866
          },
          "cp2": {
            "t": 8.667,
            "v": -1.0
          }
        }
      },
      {
        "t": 10.0,
        "v": -1.0,
        "i": null
      }
    ],
    "rot_q.x": [
      {
        "t": 0.0,
        "v": -0.0,
        "i": {
          "typ": "BAZIER",
          "cp1": {
            "t": 1.333,
            "v": -0.0
          },
          "cp2": {
            "t": 2.667,
            "v": -0.608
          }
        }
      },
      {
        "t": 4.0,
        "v": -0.608,
        "i": {
          "typ": "BAZIER",
          "cp1": {
            "t": 4.667,
            "v": -0.608
          },
          "cp2": {
            "t": 5.333,
            "v": -0.498
          }
        }
      },
      {
        "t": 6.0,
        "v": -0.394,
        "i": {
          "typ": "BAZIER",
          "cp1": {
            "t": 7.333,
            "v": -0.186
          },
          "cp2": {
            "t": 8.667,
            "v": -0.0
          }
        }
      },
      {
        "t": 10.0,
        "v": -0.0,
        "i": null
      }
    ],
    "rot_q.y": [
      {
        "t": 0.0,
        "v": 0.0,
        "i": {
          "typ": "BAZIER",
          "cp1": {
            "t": 1.333,
            "v": 0.0
          },
          "cp2": {
            "t": 2.667,
            "v": 0.0
          }
        }
      },
      {
        "t": 10.0,
        "v": 0.0,
        "i": null
      }
    ],
    "rot_q.z": [
      {
        "t": 0.0,
        "v": -0.0,
        "i": {
          "typ": "BAZIER",
          "cp1": {
            "t": 1.333,
            "v": -0.0
          },
          "cp2": {
            "t": 2.667,
            "v": 0.0
          }
        }
      },
      {
        "t": 10.0,
        "v": -0.0,
        "i": null
      }
    ]
  },
  "Head": {
    "loc.x": [
      {
        "t": 0.0,
        "v": -0.0,
        "i": {
          "typ": "BAZIER",
          "cp1": {
            "t": 1.333,
            "v": -0.0
          },
          "cp2": {
            "t": 2.667,
            "v": -0.0
          }
        }
      },
      {
        "t": 10.0,
        "v": -0.0,
        "i": null
      }
    ],
    "loc.y": [
      {
        "t": 0.0,
        "v": 0.0,
        "i": {
          "typ": "BAZIER",
          "cp1": {
            "t": 1.333,
            "v": 0.0
          },
          "cp2": {
            "t": 2.667,
            "v": 0.0
          }
        }
      },
      {
        "t": 10.0,
        "v": 0.0,
        "i": null
      }
    ],
    "loc.z": [
      {
        "t": 0.0,
        "v": -0.0,
        "i": {
          "typ": "BAZIER",
          "cp1": {
            "t": 1.333,
            "v": -0.0
          },
          "cp2": {
            "t": 2.667,
            "v": -0.0
          }
        }
      },
      {
        "t": 10.0,
        "v": -0.0,
        "i": null
      }
    ],
    "rot_q.w": [
      {
        "t": 0.0,
        "v": 1.0,
        "i": {
          "typ": "BAZIER",
          "cp1": {
            "t": 1.333,
            "v": 1.0
          },
          "cp2": {
            "t": 2.667,
            "v": 0.851
          }
        }
      },
      {
        "t": 4.0,
        "v": 0.851,
        "i": {
          "typ": "BAZIER",
          "cp1": {
            "t": 5.333,
            "v": 0.851
          },
          "cp2": {
            "t": 6.667,
            "v": 0.851
          }
        }
      },
      {
        "t": 8.0,
        "v": 0.901,
        "i": {
          "typ": "BAZIER",
          "cp1": {
            "t": 8.667,
            "v": 0.926
          },
          "cp2": {
            "t": 9.333,
            "v": 1.0
          }
        }
      },
      {
        "t": 10.0,
        "v": 1.0,
        "i": null
      }
    ],
    "rot_q.x": [
      {
        "t": 0.0,
        "v": -0.0,
        "i": {
          "typ": "BAZIER",
          "cp1": {
            "t": 1.333,
            "v": -0.0
          },
          "cp2": {
            "t": 2.667,
            "v": -0.526
          }
        }
      },
      {
        "t": 4.0,
        "v": -0.526,
        "i": {
          "typ": "BAZIER",
          "cp1": {
            "t": 5.333,
            "v": -0.526
          },
          "cp2": {
            "t": 6.667,
            "v": -0.526
          }
        }
      },
      {
        "t": 8.0,
        "v": -0.363,
        "i": {
          "typ": "BAZIER",
          "cp1": {
            "t": 8.667,
            "v": -0.281
          },
          "cp2": {
            "t": 9.333,
            "v": -0.0
          }
        }
      },
      {
        "t": 10.0,
        "v": -0.0,
        "i": null
      }
    ],
    "rot_q.y": [
      {
        "t": 0.0,
        "v": 0.0,
        "i": {
          "typ": "BAZIER",
          "cp1": {
            "t": 1.333,
            "v": 0.0
          },
          "cp2": {
            "t": 2.667,
            "v": 0.0
          }
        }
      },
      {
        "t": 10.0,
        "v": 0.0,
        "i": null
      }
    ],
    "rot_q.z": [
      {
        "t": 0.0,
        "v": -0.0,
        "i": {
          "typ": "BAZIER",
          "cp1": {
            "t": 1.333,
            "v": -0.0
          },
          "cp2": {
            "t": 2.667,
            "v": 0.0
          }
        }
      },
      {
        "t": 10.0,
        "v": -0.0,
        "i": null
      }
    ]
  },
  "Right Arm": {
    "loc.x": [
      {
        "t": 0.0,
        "v": -0.0,
        "i": {
          "typ": "BAZIER",
          "cp1": {
            "t": 0.667,
            "v": -0.0
          },
          "cp2": {
            "t": 1.333,
            "v": 0.0
          }
        }
      },
      {
        "t": 5.0,
        "v": -0.024,
        "i": {
          "typ": "BAZIER",
          "cp1": {
            "t": 6.667,
            "v": -0.024
          },
          "cp2": {
            "t": 8.333,
            "v": -0.0
          }
        }
      },
      {
        "t": 10.0,
        "v": -0.0,
        "i": null
      }
    ],
    "loc.y": [
      {
        "t": 0.0,
        "v": -0.0,
        "i": {
          "typ": "BAZIER",
          "cp1": {
            "t": 0.667,
            "v": -0.0
          },
          "cp2": {
            "t": 1.333,
            "v": 0.05
          }
        }
      },
      {
        "t": 2.0,
        "v": 0.05,
        "i": {
          "typ": "BAZIER",
          "cp1": {
            "t": 3.0,
            "v": 0.05
          },
          "cp2": {
            "t": 4.0,
            "v": -0.06
          }
        }
      },
      {
        "t": 5.0,
        "v": -0.06,
        "i": {
          "typ": "BAZIER",
          "cp1": {
            "t": 6.667,
            "v": -0.06
          },
          "cp2": {
            "t": 8.333,
            "v": -0.0
          }
        }
      },
      {
        "t": 10.0,
        "v": -0.0,
        "i": null
      }
    ],
    "loc.z": [
      {
        "t": 0.0,
        "v": 0.0,
        "i": {
          "typ": "BAZIER",
          "cp1": {
            "t": 0.667,
            "v": 0.0
          },
          "cp2": {
            "t": 1.333,
            "v": -0.092
          }
        }
      },
      {
        "t": 2.0,
        "v": -0.111,
        "i": {
          "typ": "BAZIER",
          "cp1": {
            "t": 3.0,
            "v": -0.139
          },
          "cp2": {
            "t": 4.0,
            "v": -0.139
          }
        }
      },
      {
        "t": 5.0,
        "v": -0.139,
        "i": {
          "typ": "BAZIER",
          "cp1": {
            "t": 6.667,
            "v": -0.139
          },
          "cp2": {
            "t": 8.333,
            "v": 0.0
          }
        }
      },
      {
        "t": 10.0,
        "v": 0.0,
        "i": null
      }
    ],
    "rot_q.w": [
      {
        "t": 0.0,
        "v": 1.0,
        "i": {
          "typ": "BAZIER",
          "cp1": {
            "t": 0.667,
            "v": 1.0
          },
          "cp2": {
            "t": 1.333,
            "v": 0.539
          }
        }
      },
      {
        "t": 2.0,
        "v": 0.539,
        "i": {
          "typ": "BAZIER",
          "cp1": {
            "t": 3.0,
            "v": 0.539
          },
          "cp2": {
            "t": 4.0,
            "v": 0.853
          }
        }
      },
      {
        "t": 5.0,
        "v": 0.908,
        "i": {
          "typ": "BAZIER",
          "cp1": {
            "t": 6.667,
            "v": 1.0
          },
          "cp2": {
            "t": 8.333,
            "v": 1.0
          }
        }
      },
      {
        "t": 10.0,
        "v": 1.0,
        "i": null
      }
    ],
    "rot_q.x": [
      {
        "t": 0.0,
        "v": -0.0,
        "i": {
          "typ": "BAZIER",
          "cp1": {
            "t": 0.667,
            "v": -0.0
          },
          "cp2": {
            "t": 1.333,
            "v": 0.816
          }
        }
      },
      {
        "t": 2.0,
        "v": 0.816,
        "i": {
          "typ": "BAZIER",
          "cp1": {
            "t": 3.0,
            "v": 0.816
          },
          "cp2": {
            "t": 4.0,
            "v": 0.58
          }
        }
      },
      {
        "t": 5.0,
        "v": 0.407,
        "i": {
          "typ": "BAZIER",
          "cp1": {
            "t": 6.667,
            "v": 0.118
          },
          "cp2": {
            "t": 8.333,
            "v": -0.0
          }
        }
      },
      {
        "t": 10.0,
        "v": -0.0,
        "i": null
      }
    ],
    "rot_q.y": [
      {
        "t": 0.0,
        "v": -0.0,
        "i": {
          "typ": "BAZIER",
          "cp1": {
            "t": 0.667,
            "v": -0.0
          },
          "cp2": {
            "t": 1.333,
            "v": 0.0
          }
        }
      },
      {
        "t": 5.0,
        "v": 0.043,
        "i": {
          "typ": "BAZIER",
          "cp1": {
            "t": 6.667,
            "v": 0.043
          },
          "cp2": {
            "t": 8.333,
            "v": -0.0
          }
        }
      },
      {
        "t": 10.0,
        "v": -0.0,
        "i": null
      }
    ],
    "rot_q.z": [
      {
        "t": 0.0,
        "v": 0.0,
        "i": {
          "typ": "BAZIER",
          "cp1": {
            "t": 0.667,
            "v": 0.0
          },
          "cp2": {
            "t": 1.333,
            "v": 0.0
          }
        }
      },
      {
        "t": 5.0,
        "v": -0.091,
        "i": {
          "typ": "BAZIER",
          "cp1": {
            "t": 6.667,
            "v": -0.091
          },
          "cp2": {
            "t": 8.333,
            "v": 0.0
          }
        }
      },
      {
        "t": 10.0,
        "v": 0.0,
        "i": null
      }
    ]
  },
  "Left Arm": {
    "loc.x": [
      {
        "t": 0.0,
        "v": -0.0,
        "i": {
          "typ": "BAZIER",
          "cp1": {
            "t": 0.667,
            "v": -0.0
          },
          "cp2": {
            "t": 1.333,
            "v": -0.0
          }
        }
      },
      {
        "t": 5.0,
        "v": 0.018,
        "i": {
          "typ": "BAZIER",
          "cp1": {
            "t": 5.667,
            "v": 0.018
          },
          "cp2": {
            "t": 6.333,
            "v": 0.0
          }
        }
      },
      {
        "t": 7.0,
        "v": 0.0,
        "i": {
          "typ": "BAZIER",
          "cp1": {
            "t": 8.0,
            "v": -0.0
          },
          "cp2": {
            "t": 9.0,
            "v": -0.0
          }
        }
      },
      {
        "t": 10.0,
        "v": -0.0,
        "i": null
      }
    ],
    "loc.y": [
      {
        "t": 0.0,
        "v": -0.0,
        "i": {
          "typ": "BAZIER",
          "cp1": {
            "t": 0.667,
            "v": -0.0
          },
          "cp2": {
            "t": 1.333,
            "v": 0.026
          }
        }
      },
      {
        "t": 2.0,
        "v": 0.026,
        "i": {
          "typ": "BAZIER",
          "cp1": {
            "t": 3.0,
            "v": 0.026
          },
          "cp2": {
            "t": 4.0,
            "v": -0.053
          }
        }
      },
      {
        "t": 5.0,
        "v": -0.053,
        "i": {
          "typ": "BAZIER",
          "cp1": {
            "t": 5.667,
            "v": -0.053
          },
          "cp2": {
            "t": 6.333,
            "v": -0.041
          }
        }
      },
      {
        "t": 7.0,
        "v": -0.03,
        "i": {
          "typ": "BAZIER",
          "cp1": {
            "t": 8.0,
            "v": -0.014
          },
          "cp2": {
            "t": 9.0,
            "v": -0.0
          }
        }
      },
      {
        "t": 10.0,
        "v": -0.0,
        "i": null
      }
    ],
    "loc.z": [
      {
        "t": 0.0,
        "v": 0.0,
        "i": {
          "typ": "BAZIER",
          "cp1": {
            "t": 0.667,
            "v": 0.0
          },
          "cp2": {
            "t": 1.333,
            "v": -0.115
          }
        }
      },
      {
        "t": 2.0,
        "v": -0.127,
        "i": {
          "typ": "BAZIER",
          "cp1": {
            "t": 3.0,
            "v": -0.146
          },
          "cp2": {
            "t": 4.0,
            "v": -0.146
          }
        }
      },
      {
        "t": 5.0,
        "v": -0.146,
        "i": {
          "typ": "BAZIER",
          "cp1": {
            "t": 5.667,
            "v": -0.146
          },
          "cp2": {
            "t": 6.333,
            "v": -0.043
          }
        }
      },
      {
        "t": 7.0,
        "v": -0.026,
        "i": {
          "typ": "BAZIER",
          "cp1": {
            "t": 8.0,
            "v": 0.0
          },
          "cp2": {
            "t": 9.0,
            "v": 0.0
          }
        }
      },
      {
        "t": 10.0,
        "v": 0.0,
        "i": null
      }
    ],
    "rot_q.w": [
      {
        "t": 0.0,
        "v": 1.0,
        "i": {
          "typ": "BAZIER",
          "cp1": {
            "t": 0.667,
            "v": 1.0
          },
          "cp2": {
            "t": 1.333,
            "v": 0.47
          }
        }
      },
      {
        "t": 2.0,
        "v": 0.47,
        "i": {
          "typ": "BAZIER",
          "cp1": {
            "t": 3.0,
            "v": 0.47
          },
          "cp2": {
            "t": 4.0,
            "v": 0.724
          }
        }
      },
      {
        "t": 5.0,
        "v": 0.832,
        "i": {
          "typ": "BAZIER",
          "cp1": {
            "t": 5.667,
            "v": 0.903
          },
          "cp2": {
            "t": 6.333,
            "v": 0.91
          }
        }
      },
      {
        "t": 7.0,
        "v": 0.927,
        "i": {
          "typ": "BAZIER",
          "cp1": {
            "t": 8.0,
            "v": 0.952
          },
          "cp2": {
            "t": 9.0,
            "v": 1.0
          }
        }
      },
      {
        "t": 10.0,
        "v": 1.0,
        "i": null
      }
    ],
    "rot_q.x": [
      {
        "t": 0.0,
        "v": -0.0,
        "i": {
          "typ": "BAZIER",
          "cp1": {
            "t": 0.667,
            "v": -0.0
          },
          "cp2": {
            "t": 1.333,
            "v": 0.836
          }
        }
      },
      {
        "t": 2.0,
        "v": 0.836,
        "i": {
          "typ": "BAZIER",
          "cp1": {
            "t": 3.0,
            "v": 0.836
          },
          "cp2": {
            "t": 4.0,
            "v": 0.836
          }
        }
      },
      {
        "t": 5.0,
        "v": 0.54,
        "i": {
          "typ": "BAZIER",
          "cp1": {
            "t": 5.667,
            "v": 0.344
          },
          "cp2": {
            "t": 6.333,
            "v": -0.245
          }
        }
      },
      {
        "t": 7.0,
        "v": -0.245,
        "i": {
          "typ": "BAZIER",
          "cp1": {
            "t": 8.0,
            "v": -0.245
          },
          "cp2": {
            "t": 9.0,
            "v": -0.0
          }
        }
      },
      {
        "t": 10.0,
        "v": -0.0,
        "i": null
      }
    ],
    "rot_q.y": [
      {
        "t": 0.0,
        "v": -0.0,
        "i": {
          "typ": "BAZIER",
          "cp1": {
            "t": 0.667,
            "v": -0.0
          },
          "cp2": {
            "t": 1.333,
            "v": 0.0
          }
        }
      },
      {
        "t": 5.0,
        "v": -0.036,
        "i": {
          "typ": "BAZIER",
          "cp1": {
            "t": 5.667,
            "v": -0.036
          },
          "cp2": {
            "t": 6.333,
            "v": 0.0
          }
        }
      },
      {
        "t": 7.0,
        "v": 0.0,
        "i": {
          "typ": "BAZIER",
          "cp1": {
            "t": 8.0,
            "v": 0.0
          },
          "cp2": {
            "t": 9.0,
            "v": -0.0
          }
        }
      },
      {
        "t": 10.0,
        "v": -0.0,
        "i": null
      }
    ],
    "rot_q.z": [
      {
        "t": 0.0,
        "v": 0.0,
        "i": {
          "typ": "BAZIER",
          "cp1": {
            "t": 0.667,
            "v": 0.0
          },
          "cp2": {
            "t": 1.333,
            "v": 0.0
          }
        }
      },
      {
        "t": 5.0,
        "v": 0.122,
        "i": {
          "typ": "BAZIER",
          "cp1": {
            "t": 5.667,
            "v": 0.122
          },
          "cp2": {
            "t": 6.333,
            "v": -0.0
          }
        }
      },
      {
        "t": 7.0,
        "v": -0.0,
        "i": {
          "typ": "BAZIER",
          "cp1": {
            "t": 8.0,
            "v": -0.0
          },
          "cp2": {
            "t": 9.0,
            "v": 0.0
          }
        }
      },
      {
        "t": 10.0,
        "v": 0.0,
        "i": null
      }
    ]
  },
  "Right Leg": {
    "loc.x": [
      {
        "t": 0.0,
        "v": -0.0,
        "i": {
          "typ": "BAZIER",
          "cp1": {
            "t": 0.667,
            "v": -0.0
          },
          "cp2": {
            "t": 1.333,
            "v": -0.0
          }
        }
      },
      {
        "t": 10.0,
        "v": -0.0,
        "i": null
      }
    ],
    "loc.y": [
      {
        "t": 0.0,
        "v": -0.0,
        "i": {
          "typ": "BAZIER",
          "cp1": {
            "t": 0.667,
            "v": -0.0
          },
          "cp2": {
            "t": 1.333,
            "v": 0.021
          }
        }
      },
      {
        "t": 2.0,
        "v": 0.109,
        "i": {
          "typ": "BAZIER",
          "cp1": {
            "t": 2.667,
            "v": 0.197
          },
          "cp2": {
            "t": 3.333,
            "v": 0.352
          }
        }
      },
      {
        "t": 4.0,
        "v": 0.352,
        "i": {
          "typ": "BAZIER",
          "cp1": {
            "t": 5.0,
            "v": 0.352
          },
          "cp2": {
            "t": 6.0,
            "v": 0.133
          }
        }
      },
      {
        "t": 7.0,
        "v": 0.067,
        "i": {
          "typ": "BAZIER",
          "cp1": {
            "t": 8.0,
            "v": -0.0
          },
          "cp2": {
            "t": 9.0,
            "v": -0.0
          }
        }
      },
      {
        "t": 10.0,
        "v": -0.0,
        "i": null
      }
    ],
    "loc.z": [
      {
        "t": 0.0,
        "v": 0.0,
        "i": {
          "typ": "BAZIER",
          "cp1": {
            "t": 0.667,
            "v": 0.0
          },
          "cp2": {
            "t": 1.333,
            "v": -0.111
          }
        }
      },
      {
        "t": 2.0,
        "v": -0.171,
        "i": {
          "typ": "BAZIER",
          "cp1": {
            "t": 2.667,
            "v": -0.232
          },
          "cp2": {
            "t": 3.333,
            "v": -0.243
          }
        }
      },
      {
        "t": 4.0,
        "v": -0.243,
        "i": {
          "typ": "BAZIER",
          "cp1": {
            "t": 5.0,
            "v": -0.243
          },
          "cp2": {
            "t": 6.0,
            "v": -0.233
          }
        }
      },
      {
        "t": 7.0,
        "v": -0.172,
        "i": {
          "typ": "BAZIER",
          "cp1": {
            "t": 8.0,
            "v": -0.111
          },
          "cp2": {
            "t": 9.0,
            "v": 0.0
          }
        }
      },
      {
        "t": 10.0,
        "v": 0.0,
        "i": null
      }
    ],
    "rot_q.w": [
      {
        "t": 0.0,
        "v": 1.0,
        "i": {
          "typ": "BAZIER",
          "cp1": {
            "t": 0.667,
            "v": 1.0
          },
          "cp2": {
            "t": 1.333,
            "v": 0.969
          }
        }
      },
      {
        "t": 2.0,
        "v": 0.969,
        "i": {
          "typ": "BAZIER",
          "cp1": {
            "t": 2.667,
            "v": 0.969
          },
          "cp2": {
            "t": 3.333,
            "v": 0.999
          }
        }
      },
      {
        "t": 4.0,
        "v": 0.999,
        "i": {
          "typ": "BAZIER",
          "cp1": {
            "t": 5.0,
            "v": 0.999
          },
          "cp2": {
            "t": 6.0,
            "v": 0.971
          }
        }
      },
      {
        "t": 7.0,
        "v": 0.971,
        "i": {
          "typ": "BAZIER",
          "cp1": {
            "t": 8.0,
            "v": 0.971
          },
          "cp2": {
            "t": 9.0,
            "v": 1.0
          }
        }
      },
      {
        "t": 10.0,
        "v": 1.0,
        "i": null
      }
    ],
    "rot_q.x": [
      {
        "t": 0.0,
        "v": -0.0,
        "i": {
          "typ": "BAZIER",
          "cp1": {
            "t": 0.667,
            "v": -0.0
          },
          "cp2": {
            "t": 1.333,
            "v": 0.247
          }
        }
      },
      {
        "t": 2.0,
        "v": 0.247,
        "i": {
          "typ": "BAZIER",
          "cp1": {
            "t": 2.667,
            "v": 0.247
          },
          "cp2": {
            "t": 3.333,
            "v": -0.042
          }
        }
      },
      {
        "t": 4.0,
        "v": -0.042,
        "i": {
          "typ": "BAZIER",
          "cp1": {
            "t": 5.0,
            "v": -0.042
          },
          "cp2": {
            "t": 6.0,
            "v": 0.239
          }
        }
      },
      {
        "t": 7.0,
        "v": 0.239,
        "i": {
          "typ": "BAZIER",
          "cp1": {
            "t": 8.0,
            "v": 0.239
          },
          "cp2": {
            "t": 9.0,
            "v": -0.0
          }
        }
      },
      {
        "t": 10.0,
        "v": -0.0,
        "i": null
      }
    ],
    "rot_q.y": [
      {
        "t": 0.0,
        "v": -0.0,
        "i": {
          "typ": "BAZIER",
          "cp1": {
            "t": 0.667,
            "v": -0.0
          },
          "cp2": {
            "t": 1.333,
            "v": -0.0
          }
        }
      },
      {
        "t": 10.0,
        "v": -0.0,
        "i": null
      }
    ],
    "rot_q.z": [
      {
        "t": 0.0,
        "v": 0.0,
        "i": {
          "typ": "BAZIER",
          "cp1": {
            "t": 0.667,
            "v": 0.0
          },
          "cp2": {
            "t": 1.333,
            "v": 0.0
          }
        }
      },
      {
        "t": 10.0,
        "v": 0.0,
        "i": null
      }
    ]
  },
  "Left Leg": {
    "loc.x": [
      {
        "t": 0.0,
        "v": -0.0,
        "i": {
          "typ": "BAZIER",
          "cp1": {
            "t": 0.667,
            "v": -0.0
          },
          "cp2": {
            "t": 1.333,
            "v": 0.0
          }
        }
      },
      {
        "t": 10.0,
        "v": -0.0,
        "i": null
      }
    ],
    "loc.y": [
      {
        "t": 0.0,
        "v": -0.0,
        "i": {
          "typ": "BAZIER",
          "cp1": {
            "t": 0.667,
            "v": -0.0
          },
          "cp2": {
            "t": 1.333,
            "v": 0.082
          }
        }
      },
      {
        "t": 2.0,
        "v": 0.168,
        "i": {
          "typ": "BAZIER",
          "cp1": {
            "t": 2.667,
            "v": 0.255
          },
          "cp2": {
            "t": 3.333,
            "v": 0.347
          }
        }
      },
      {
        "t": 4.0,
        "v": 0.347,
        "i": {
          "typ": "BAZIER",
          "cp1": {
            "t": 5.0,
            "v": 0.347
          },
          "cp2": {
            "t": 6.0,
            "v": 0.098
          }
        }
      },
      {
        "t": 7.0,
        "v": 0.049,
        "i": {
          "typ": "BAZIER",
          "cp1": {
            "t": 8.0,
            "v": -0.0
          },
          "cp2": {
            "t": 9.0,
            "v": -0.0
          }
        }
      },
      {
        "t": 10.0,
        "v": -0.0,
        "i": null
      }
    ],
    "loc.z": [
      {
        "t": 0.0,
        "v": 0.0,
        "i": {
          "typ": "BAZIER",
          "cp1": {
            "t": 0.667,
            "v": 0.0
          },
          "cp2": {
            "t": 1.333,
            "v": -0.195
          }
        }
      },
      {
        "t": 2.0,
        "v": -0.195,
        "i": {
          "typ": "BAZIER",
          "cp1": {
            "t": 2.667,
            "v": -0.195
          },
          "cp2": {
            "t": 3.333,
            "v": -0.188
          }
        }
      },
      {
        "t": 4.0,
        "v": -0.188,
        "i": {
          "typ": "BAZIER",
          "cp1": {
            "t": 5.0,
            "v": -0.188
          },
          "cp2": {
            "t": 6.0,
            "v": -0.218
          }
        }
      },
      {
        "t": 7.0,
        "v": -0.218,
        "i": {
          "typ": "BAZIER",
          "cp1": {
            "t": 8.0,
            "v": -0.218
          },
          "cp2": {
            "t": 9.0,
            "v": 0.0
          }
        }
      },
      {
        "t": 10.0,
        "v": 0.0,
        "i": null
      }
    ],
    "rot_q.w": [
      {
        "t": 0.0,
        "v": 1.0,
        "i": {
          "typ": "BAZIER",
          "cp1": {
            "t": 0.667,
            "v": 1.0
          },
          "cp2": {
            "t": 1.333,
            "v": 0.93
          }
        }
      },
      {
        "t": 2.0,
        "v": 0.93,
        "i": {
          "typ": "BAZIER",
          "cp1": {
            "t": 2.667,
            "v": 0.93
          },
          "cp2": {
            "t": 3.333,
            "v": 0.992
          }
        }
      },
      {
        "t": 4.0,
        "v": 0.992,
        "i": {
          "typ": "BAZIER",
          "cp1": {
            "t": 5.0,
            "v": 0.992
          },
          "cp2": {
            "t": 6.0,
            "v": 0.915
          }
        }
      },
      {
        "t": 7.0,
        "v": 0.915,
        "i": {
          "typ": "BAZIER",
          "cp1": {
            "t": 8.0,
            "v": 0.915
          },
          "cp2": {
            "t": 9.0,
            "v": 1.0
          }
        }
      },
      {
        "t": 10.0,
        "v": 1.0,
        "i": null
      }
    ],
    "rot_q.x": [
      {
        "t": 0.0,
        "v": -0.0,
        "i": {
          "typ": "BAZIER",
          "cp1": {
            "t": 0.667,
            "v": -0.0
          },
          "cp2": {
            "t": 1.333,
            "v": 0.361
          }
        }
      },
      {
        "t": 2.0,
        "v": 0.361,
        "i": {
          "typ": "BAZIER",
          "cp1": {
            "t": 2.667,
            "v": 0.361
          },
          "cp2": {
            "t": 3.333,
            "v": -0.125
          }
        }
      },
      {
        "t": 4.0,
        "v": -0.125,
        "i": {
          "typ": "BAZIER",
          "cp1": {
            "t": 5.0,
            "v": -0.125
          },
          "cp2": {
            "t": 6.0,
            "v": 0.422
          }
        }
      },
      {
        "t": 7.0,
        "v": 0.422,
        "i": {
          "typ": "BAZIER",
          "cp1": {
            "t": 8.0,
            "v": 0.422
          },
          "cp2": {
            "t": 9.0,
            "v": -0.0
          }
        }
      },
      {
        "t": 10.0,
        "v": -0.0,
        "i": null
      }
    ],
    "rot_q.y": [
      {
        "t": 0.0,
        "v": -0.0,
        "i": {
          "typ": "BAZIER",
          "cp1": {
            "t": 0.667,
            "v": -0.0
          },
          "cp2": {
            "t": 1.333,
            "v": 0.0
          }
        }
      },
      {
        "t": 10.0,
        "v": -0.0,
        "i": null
      }
    ],
    "rot_q.z": [
      {
        "t": 0.0,
        "v": 0.0,
        "i": {
          "typ": "BAZIER",
          "cp1": {
            "t": 0.667,
            "v": 0.0
          },
          "cp2": {
            "t": 1.333,
            "v": 0.0
          }
        }
      },
      {
        "t": 10.0,
        "v": 0.0,
        "i": null
      }
    ]
  }
}