{
  "Body": {
    "loc.x": [
      {
        "t": 0.0,
        "v": -0.0,
        "i": {
          "typ": "BAZIER",
          "cp1": {
            "t": 1.667,
            "v": -0.0
          },
          "cp2": {
            "t": 3.333,
            "v": -0.0
          }
        }
      },
      {
        "t": 10.0,
        "v": -0.0,
        "i": null
      }
    ],
    "loc.y": [
      {
        "t": 0.0,
        "v": -0.664,
        "i": {
          "typ": "BAZIER",
          "cp1": {
            "t": 1.667,
            "v": -0.664
          },
          "cp2": {
            "t": 3.333,
            "v": -0.664
          }
        }
      },
      {
        "t": 10.0,
        "v": -0.664,
        "i": null
      }
    ],
    "loc.z": [
      {
        "t": 0.0,
        "v": -0.0,
        "i": {
          "typ": "BAZIER",
          "cp1": {
            "t": 1.667,
            "v": -0.0
          },
          "cp2": {
            "t": 3.333,
            "v": -0.0
          }
        }
      },
      {
        "t": 10.0,
        "v": -0.0,
        "i": null
      }
    ],
    "rot_q.w": [
      {
        "t": 0.0,
        "v": 0.53,
        "i": {
          "typ": "BAZIER",
          "cp1": {
            "t": 1.667,
            "v": 0.53
          },
          "cp2": {
            "t": 3.333,
            "v": 0.555
          }
        }
      },
      {
        "t": 5.0,
        "v": 0.555,
        "i": {
          "typ": "BAZIER",
          "cp1": {
            "t": 6.667,
            "v": 0.555
          },
          "cp2": {
            "t": 8.333,
            "v": 0.53
          }
        }
      },
      {
        "t": 10.0,
        "v": 0.53,
        "i": null
      }
    ],
    "rot_q.x": [
      {
        "t": 0.0,
        "v": -0.848,
        "i": {
          "typ": "BAZIER",
          "cp1": {
            "t": 1.667,
            "v": -0.848
          },
          "cp2": {
            "t": 3.333,
            "v": -0.832
          }
        }
      },
      {
        "t": 5.0,
        "v": -0.832,
        "i": {
          "typ": "BAZIER",
          "cp1": {
            "t": 6.667,
            "v": -0.832
          },
          "cp2": {
            "t": 8.333,
            "v": -0.848
          }
        }
      },
      {
        "t": 10.0,
        "v": -0.848,
        "i": null
      }
    ],
    "rot_q.y": [
      {
        "t": 0.0,
        "v": 0.0,
        "i": {
          "typ": "BAZIER",
          "cp1": {
            "t": 1.667,
            "v": 0.0
          },
          "cp2": {
            "t": 3.333,
            "v": 0.0
          }
        }
      },
      {
        "t": 10.0,
        "v": 0.0,
        "i": null
      }
    ],
    "rot_q.z": [
      {
        "t": 0.0,
        "v": 0.0,
        "i": {
          "typ": "BAZIER",
          "cp1": {
            "t": 1.667,
            "v": 0.0
          },
          "cp2": {
            "t": 3.333,
            "v": 0.0
          }
        }
      },
      {
        "t": 10.0,
        "v": 0.0,
        "i": null
      }
    ]
  },
  "Head": {
    "rot_q.w": [
      {
        "t": 0.0,
        "v": 0.894,
        "i": null
      }
    ],
    "rot_q.x": [
      {
        "t": 0.0,
        "v": 0.448,
        "i": null
      }
    ]
  },
  "Right Arm": {
    "loc.x": [
      {
        "t": 0.0,
        "v": 0.0,
        "i": {
          "typ": "BAZIER",
          "cp1": {
            "t": 1.667,
            "v": 0.0
          },
          "cp2": {
            "t": 3.333,
            "v": 0.0
          }
        }
      },
      {
        "t": 10.0,
        "v": 0.0,
        "i": null
      }
    ],
    "loc.y": [
      {
        "t": 0.0,
        "v": -0.03,
        "i": {
          "typ": "BAZIER",
          "cp1": {
            "t": 1.667,
            "v": -0.03
          },
          "cp2": {
            "t": 3.333,
            "v": -0.03
          }
        }
      },
      {
        "t": 10.0,
        "v": -0.03,
        "i": null
      }
    ],
    "loc.z": [
      {
        "t": 0.0,
        "v": 0.0,
        "i": {
          "typ": "BAZIER",
          "cp1": {
            "t": 1.667,
            "v": 0.0
          },
          "cp2": {
            "t": 3.333,
            "v": 0.0
          }
        }
      },
      {
        "t": 10.0,
        "v": 0.0,
        "i": null
      }
    ],
    "rot_q.w": [
      {
        "t": 0.0,
        "v": 0.929,
        "i": {
          "typ": "BAZIER",
          "cp1": {
            "t": 1.667,
            "v": 0.929
          },
          "cp2": {
            "t": 3.333,
            "v": 0.915
          }
        }
      },
      {
        "t": 5.0,
        "v": 0.915,
        "i": {
          "typ": "BAZIER",
          "cp1": {
            "t": 6.667,
            "v": 0.915
          },
          "cp2": {
            "t": 8.333,
            "v": 0.929
          }
        }
      },
      {
        "t": 10.0,
        "v": 0.929,
        "i": null
      }
    ],
    "rot_q.x": [
      {
        "t": 0.0,
        "v": -0.118,
        "i": {
          "typ": "BAZIER",
          "cp1": {
            "t": 1.667,
            "v": -0.118
          },
          "cp2": {
            "t": 3.333,
            "v": -0.117
          }
        }
      },
      {
        "t": 5.0,
        "v": -0.117,
        "i": {
          "typ": "BAZIER",
          "cp1": {
            "t": 6.667,
            "v": -0.117
          },
          "cp2": {
            "t": 8.333,
            "v": -0.118
          }
        }
      },
      {
        "t": 10.0,
        "v": -0.118,
        "i": null
      }
    ],
    "rot_q.y": [
      {
        "t": 0.0,
        "v": 0.059,
        "i": {
          "typ": "BAZIER",
          "cp1": {
            "t": 1.667,
            "v": 0.059
          },
          "cp2": {
            "t": 3.333,
            "v": 0.064
          }
        }
      },
      {
        "t": 5.0,
        "v": 0.064,
        "i": {
          "typ": "BAZIER",
          "cp1": {
            "t": 6.667,
            "v": 0.064
          },
          "cp2": {
            "t": 8.333,
            "v": 0.059
          }
        }
      },
      {
        "t": 10.0,
        "v": 0.059,
        "i": null
      }
    ],
    "rot_q.z": [
      {
        "t": 0.0,
        "v": 0.346,
        "i": {
          "typ": "BAZIER",
          "cp1": {
            "t": 1.667,
            "v": 0.346
          },
          "cp2": {
            "t": 3.333,
            "v": 0.38
          }
        }
      },
      {
        "t": 5.0,
        "v": 0.38,
        "i": {
          "typ": "BAZIER",
          "cp1": {
            "t": 6.667,
            "v": 0.38
          },
          "cp2": {
            "t": 8.333,
            "v": 0.346
          }
        }
      },
      {
        "t": 10.0,
        "v": 0.346,
        "i": null
      }
    ]
  },
  "Left Arm": {
    "loc.x": [
      {
        "t": 0.0,
        "v": -0.0,
        "i": {
          "typ": "BAZIER",
          "cp1": {
            "t": 1.667,
            "v": -0.0
          },
          "cp2": {
            "t": 3.333,
            "v": -0.0
          }
        }
      },
      {
        "t": 10.0,
        "v": -0.0,
        "i": null
      }
    ],
    "loc.y": [
      {
        "t": 0.0,
        "v": -0.03,
        "i": {
          "typ": "BAZIER",
          "cp1": {
            "t": 1.667,
            "v": -0.03
          },
          "cp2": {
            "t": 3.333,
            "v": -0.03
          }
        }
      },
      {
        "t": 10.0,
        "v": -0.03,
        "i": null
      }
    ],
    "loc.z": [
      {
        "t": 0.0,
        "v": 0.0,
        "i": {
          "typ": "BAZIER",
          "cp1": {
            "t": 1.667,
            "v": 0.0
          },
          "cp2": {
            "t": 3.333,
            "v": 0.0
          }
        }
      },
      {
        "t": 10.0,
        "v": 0.0,
        "i": null
      }
    ],
    "rot_q.w": [
      {
        "t": 0.0,
        "v": 0.929,
        "i": {
          "typ": "BAZIER",
          "cp1": {
            "t": 1.667,
            "v": 0.929
          },
          "cp2": {
            "t": 3.333,
            "v": 0.915
          }
        }
      },
      {
        "t": 5.0,
        "v": 0.915,
        "i": {
          "typ": "BAZIER",
          "cp1": {
            "t": 6.667,
            "v": 0.915
          },
          "cp2": {
            "t": 8.333,
            "v": 0.929
          }
        }
      },
      {
        "t": 10.0,
        "v": 0.929,
        "i": null
      }
    ],
    "rot_q.x": [
      {
        "t": 0.0,
        "v": -0.118,
        "i": {
          "typ": "BAZIER",
          "cp1": {
            "t": 1.667,
            "v": -0.118
          },
          "cp2": {
            "t": 3.333,
            "v": -0.117
          }
        }
      },
      {
        "t": 5.0,
        "v": -0.117,
        "i": {
          "typ": "BAZIER",
          "cp1": {
            "t": 6.667,
            "v": -0.117
          },
          "cp2": {
            "t": 8.333,
            "v": -0.118
          }
        }
      },
      {
        "t": 10.0,
        "v": -0.118,
        "i": null
      }
    ],
    "rot_q.y": [
      {
        "t": 0.0,
        "v": -0.059,
        "i": {
          "typ": "BAZIER",
          "cp1": {
            "t": 1.667,
            "v": -0.059
          },
          "cp2": {
            "t": 3.333,
            "v": -0.064
          }
        }
      },
      {
        "t": 5.0,
        "v": -0.064,
        "i": {
          "typ": "BAZIER",
          "cp1": {
            "t": 6.667,
            "v": -0.064
          },
          "cp2": {
            "t": 8.333,
            "v": -0.059
          }
        }
      },
      {
        "t": 10.0,
        "v": -0.059,
        "i": null
      }
    ],
    "rot_q.z": [
      {
        "t": 0.0,
        "v": -0.346,
        "i": {
          "typ": "BAZIER",
          "cp1": {
            "t": 1.667,
            "v": -0.346
          },
          "cp2": {
            "t": 3.333,
            "v": -0.38
          }
        }
      },
      {
        "t": 5.0,
        "v": -0.38,
        "i": {
          "typ": "BAZIER",
          "cp1": {
            "t": 6.667,
            "v": -0.38
          },
          "cp2": {
            "t": 8.333,
            "v": -0.346
          }
        }
      },
      {
        "t": 10.0,
        "v": -0.346,
        "i": null
      }
    ]
  },
  "Right Leg": {
    "loc.x": [
      {
        "t": 0.0,
        "v": 0.043,
        "i": {
          "typ": "BAZIER",
          "cp1": {
            "t": 1.667,
            "v": 0.043
          },
          "cp2": {
            "t": 3.333,
            "v": 0.043
          }
        }
      },
      {
        "t": 10.0,
        "v": 0.043,
        "i": null
      }
    ],
    "loc.y": [
      {
        "t": 0.0,
        "v": -0.033,
        "i": {
          "typ": "BAZIER",
          "cp1": {
            "t": 1.667,
            "v": -0.033
          },
          "cp2": {
            "t": 3.333,
            "v": -0.033
          }
        }
      },
      {
        "t": 10.0,
        "v": -0.033,
        "i": null
      }
    ],
    "loc.z": [
      {
        "t": 0.0,
        "v": 0.031,
        "i": {
          "typ": "BAZIER",
          "cp1": {
            "t": 1.667,
            "v": 0.031
          },
          "cp2": {
            "t": 3.333,
            "v": 0.031
          }
        }
      },
      {
        "t": 10.0,
        "v": 0.031,
        "i": null
      }
    ],
    "rot_q.w": [
      {
        "t": 0.0,
        "v": 0.981,
        "i": {
          "typ": "BAZIER",
          "cp1": {
            "t": 1.667,
            "v": 0.981
          },
          "cp2": {
            "t": 3.333,
            "v": 0.983
          }
        }
      },
      {
        "t": 5.0,
        "v": 0.983,
        "i": {
          "typ": "BAZIER",
          "cp1": {
            "t": 6.667,
            "v": 0.983
          },
          "cp2": {
            "t": 8.333,
            "v": 0.981
          }
        }
      },
      {
        "t": 10.0,
        "v": 0.981,
        "i": null
      }
    ],
    "rot_q.x": [
      {
        "t": 0.0,
        "v": -0.151,
        "i": {
          "typ": "BAZIER",
          "cp1": {
            "t": 1.667,
            "v": -0.151
          },
          "cp2": {
            "t": 3.333,
            "v": -0.151
          }
        }
      },
      {
        "t": 5.0,
        "v": -0.151,
        "i": {
          "typ": "BAZIER",
          "cp1": {
            "t": 6.667,
            "v": -0.151
          },
          "cp2": {
            "t": 8.333,
            "v": -0.151
          }
        }
      },
      {
        "t": 10.0,
        "v": -0.151,
        "i": null
      }
    ],
    "rot_q.y": [
      {
        "t": 0.0,
        "v": 0.046,
        "i": {
          "typ": "BAZIER",
          "cp1": {
            "t": 1.667,
            "v": 0.046
          },
          "cp2": {
            "t": 3.333,
            "v": 0.045
          }
        }
      },
      {
        "t": 5.0,
        "v": 0.045,
        "i": {
          "typ": "BAZIER",
          "cp1": {
            "t": 6.667,
            "v": 0.045
          },
          "cp2": {
            "t": 8.333,
            "v": 0.046
          }
        }
      },
      {
        "t": 10.0,
        "v": 0.046,
        "i": null
      }
    ],
    "rot_q.z": [
      {
        "t": 0.0,
        "v": 0.111,
        "i": {
          "typ": "BAZIER",
          "cp1": {
            "t": 1.667,
            "v": 0.111
          },
          "cp2": {
            "t": 3.333,
            "v": 0.091
          }
        }
      },
      {
        "t": 5.0,
        "v": 0.091,
        "i": {
          "typ": "BAZIER",
          "cp1": {
            "t": 6.667,
            "v": 0.091
          },
          "cp2": {
            "t": 8.333,
            "v": 0.111
          }
        }
      },
      {
        "t": 10.0,
        "v": 0.111,
        "i": null
      }
    ]
  },
  "Left Leg": {
    "loc.x": [
      {
        "t": 0.0,
        "v": -0.043,
        "i": {
          "typ": "BAZIER",
          "cp1": {
            "t": 1.667,
            "v": -0.043
          },
          "cp2": {
            "t": 3.333,
            "v": -0.043
          }
        }
      },
      {
        "t": 10.0,
        "v": -0.043,
        "i": null
      }
    ],
    "loc.y": [
      {
        "t": 0.0,
        "v": -0.033,
        "i": {
          "typ": "BAZIER",
          "cp1": {
            "t": 1.667,
            "v": -0.033
          },
          "cp2": {
            "t": 3.333,
            "v": -0.033
          }
        }
      },
      {
        "t": 10.0,
        "v": -0.033,
        "i": null
      }
    ],
    "loc.z": [
      {
        "t": 0.0,
        "v": 0.031,
        "i": {
          "typ": "BAZIER",
          "cp1": {
            "t": 1.667,
            "v": 0.031
          },
          "cp2": {
            "t": 3.333,
            "v": 0.031
          }
        }
      },
      {
        "t": 10.0,
        "v": 0.031,
        "i": null
      }
    ],
    "rot_q.w": [
      {
        "t": 0.0,
        "v": 0.981,
        "i": {
          "typ": "BAZIER",
          "cp1": {
            "t": 1.667,
            "v": 0.981
          },
          "cp2": {
            "t": 3.333,
            "v": 0.983
          }
        }
      },
      {
        "t": 5.0,
        "v": 0.983,
        "i": {
          "typ": "BAZIER",
          "cp1": {
            "t": 6.667,
            "v": 0.983
          },
          "cp2": {
            "t": 8.333,
            "v": 0.981
          }
        }
      },
      {
        "t": 10.0,
        "v": 0.981,
        "i": null
      }
    ],
    "rot_q.x": [
      {
        "t": 0.0,
        "v": -0.151,
        "i": {
          "typ": "BAZIER",
          "cp1": {
            "t": 1.667,
            "v": -0.151
          },
          "cp2": {
            "t": 3.333,
            "v": -0.151
          }
        }
      },
      {
        "t": 5.0,
        "v": -0.151,
        "i": {
          "typ": "BAZIER",
          "cp1": {
            "t": 6.667,
            "v": -0.151
          },
          "cp2": {
            "t": 8.333,
            "v": -0.151
          }
        }
      },
      {
        "t": 10.0,
        "v": -0.151,
        "i": null
      }
    ],
    "rot_q.y": [
      {
        "t": 0.0,
        "v": -0.046,
        "i": {
          "typ": "BAZIER",
          "cp1": {
            "t": 1.667,
            "v": -0.046
          },
          "cp2": {
            "t": 3.333,
            "v": -0.045
          }
        }
      },
      {
        "t": 5.0,
        "v": -0.045,
        "i": {
          "typ": "BAZIER",
          "cp1": {
            "t": 6.667,
            "v": -0.045
          },
          "cp2": {
            "t": 8.333,
            "v": -0.046
          }
        }
      },
      {
        "t": 10.0,
        "v": -0.046,
        "i": null
      }
    ],
    "rot_q.z": [
      {
        "t": 0.0,
        "v": -0.111,
        "i": {
          "typ": "BAZIER",
          "cp1": {
            "t": 1.667,
            "v": -0.111
          },
          "cp2": {
            "t": 3.333,
            "v": -0.091
          }
        }
      },
      {
        "t": 5.0,
        "v": -0.091,
        "i": {
          "typ": "BAZIER",
          "cp1": {
            "t": 6.667,
            "v": -0.091
          },
          "cp2": {
            "t": 8.333,
            "v": -0.111
          }
        }
      },
      {
        "t": 10.0,
        "v": -0.111,
        "i": null
      }
    ]
  }
}